yieldlocus.py
yieldlocus-1.0.0.dist-info/LICENSE
yieldlocus-1.0.0.dist-info/METADATA
yieldlocus-1.0.0.dist-info/WHEEL
yieldlocus-1.0.0.dist-info/top_level.txt
yieldlocus-1.0.0.dist-info/RECORD
