Metadata-Version: 2.1
Name: yieldlocus
Version: 1.0.0
Summary: Plotting yield locus for various test results
Home-page: https://github.com/omkar-salunke/yield_locus/
Author: omkar_salunke
Author-email: ossalunke@gmail.com
License: MIT
Download-URL: https://github.com/omkar-salunke/yield_locus/archive/v{}.tar.gz
Platform: UNKNOWN
Classifier: Intended Audience :: Science/Research
Classifier: License :: OSI Approved :: MIT License
Classifier: Operating System :: OS Independent
Classifier: Programming Language :: Python
Classifier: Programming Language :: Python :: 2.7
Classifier: Programming Language :: Python :: 3.4
Classifier: Programming Language :: Python :: 3.5
Classifier: Programming Language :: Python :: 3.6
Classifier: Programming Language :: Python :: 3.7
Classifier: Programming Language :: Python :: 3.8
Classifier: Topic :: Scientific/Engineering
Classifier: Topic :: Software Development :: Libraries :: Python Modules
